LICENSE.txt
README.txt
TODO.txt
setup.cfg
setup.py
docs/HISTORY.txt
pcommerce/__init__.py
pcommerce.payment.ogone.egg-info/PKG-INFO
pcommerce.payment.ogone.egg-info/SOURCES.txt
pcommerce.payment.ogone.egg-info/dependency_links.txt
pcommerce.payment.ogone.egg-info/entry_points.txt
pcommerce.payment.ogone.egg-info/namespace_packages.txt
pcommerce.payment.ogone.egg-info/not-zip-safe
pcommerce.payment.ogone.egg-info/requires.txt
pcommerce.payment.ogone.egg-info/top_level.txt
pcommerce/payment/__init__.py
pcommerce/payment/ogone/__init__.py
pcommerce/payment/ogone/configure.zcml
pcommerce/payment/ogone/controlpanel.py
pcommerce/payment/ogone/data.py
pcommerce/payment/ogone/exceptions.py
pcommerce/payment/ogone/interfaces.py
pcommerce/payment/ogone/plugin.py
pcommerce/payment/ogone/security.py
pcommerce/payment/ogone/status_codes.py
pcommerce/payment/ogone/browser/__init__.py
pcommerce/payment/ogone/browser/configure.zcml
pcommerce/payment/ogone/browser/confirmation.pt
pcommerce/payment/ogone/browser/confirmation.py
pcommerce/payment/ogone/browser/icon.jpg
pcommerce/payment/ogone/browser/logo.jpg
pcommerce/payment/ogone/browser/overview.pt
pcommerce/payment/ogone/browser/overview.py
pcommerce/payment/ogone/browser/payment.py
pcommerce/payment/ogone/browser/process.pt
pcommerce/payment/ogone/browser/process.py
pcommerce/payment/ogone/locales/additional.pot
pcommerce/payment/ogone/locales/pcommerce.payment.ogone.pot
pcommerce/payment/ogone/locales/runi18ndude.sh
pcommerce/payment/ogone/locales/nl/LC_MESSAGES/pcommerce.payment.ogone.po
pcommerce/payment/ogone/profiles/default/controlpanel.xml
pcommerce/payment/ogone/profiles/default/metadata.xml
pcommerce/payment/ogone/profiles/default/pcommerce.payment.ogone_various.txt
pcommerce/payment/ogone/profiles/default/registry.xml