Metadata-Version: 1.0
Name: pcommerce.payment.ogone
Version: 1.0a2
Summary: Ogone payment plugin for PCommerce
Home-page: http://www.gw20e.com
Author: Huub Bouma
Author-email: support@gw20e.com
License: GPL
Platform: UNKNOWN
Classifier: Programming Language :: Python
Classifier: Topic :: Software Development :: Libraries :: Python Modules
